surveytoolbox/PointStore.py
surveytoolbox/SurveyPoint.py
surveytoolbox/__init__.py
surveytoolbox/__main__.py
surveytoolbox/bdc.py
surveytoolbox/bfd.py
surveytoolbox/cbd.py
surveytoolbox/commonCalculations.py
surveytoolbox/config.py
surveytoolbox/dec.py
surveytoolbox/dms.py
surveytoolbox/dst.py
surveytoolbox/fmt_dms.py
surveytoolbox/main.py
surveytoolbox/setup.py
survey_toolbox-0.0.3.dist-info/LICENSE
survey_toolbox-0.0.3.dist-info/METADATA
survey_toolbox-0.0.3.dist-info/WHEEL
survey_toolbox-0.0.3.dist-info/top_level.txt
survey_toolbox-0.0.3.dist-info/RECORD
