Metadata-Version: 2.1
Name: survey-toolbox
Version: 0.0.3
Summary: Add surveyor mathematics easily to your projects.
Home-page: https://github.com/JayArghArgh/surveytoolbox
Author: Justin Reid
Author-email: jayarghargh@gmail.com
License: MIT
Platform: UNKNOWN
Classifier: License :: OSI Approved :: MIT License
Classifier: Programming Language :: Python :: 3
Classifier: Programming Language :: Python :: 3.7
License-File: LICENSE
